climetlab_intake/__init__.py
climetlab_intake/intake.py
climetlab_intake_plugin-0.0.1.dist-info/LICENSE
climetlab_intake_plugin-0.0.1.dist-info/METADATA
climetlab_intake_plugin-0.0.1.dist-info/WHEEL
climetlab_intake_plugin-0.0.1.dist-info/entry_points.txt
climetlab_intake_plugin-0.0.1.dist-info/top_level.txt
climetlab_intake_plugin-0.0.1.dist-info/zip-safe
climetlab_intake_plugin-0.0.1.dist-info/RECORD
